README.rst
setup.py
twtPyCurl/__init__.py
twtPyCurl.egg-info/PKG-INFO
twtPyCurl.egg-info/SOURCES.txt
twtPyCurl.egg-info/dependency_links.txt
twtPyCurl.egg-info/not-zip-safe
twtPyCurl.egg-info/requires.txt
twtPyCurl.egg-info/top_level.txt
twtPyCurl/../twt_data/help_configuration.json
twtPyCurl/../twt_data/sample_credentials_application.json
twtPyCurl/../twt_data/sample_credentials_user.json
twtPyCurl/../twt_data/tweets_sample_10000.json.gz
twtPyCurl/../twt_data/twt_endpoints_rest.txt
twtPyCurl/../twt_data/twt_endpoints_stream.txt
twtPyCurl/py/__init__.py
twtPyCurl/py/oauth.py
twtPyCurl/py/requests.py
twtPyCurl/py/utilities.py
twtPyCurl/tests/REST.py
twtPyCurl/tests/__init__.py
twtPyCurl/tests/manual.py
twtPyCurl/twt/__init__.py
twtPyCurl/twt/clients.py
twtPyCurl/twt/constants.py
twtPyCurl/twt/endpoints.py
twtPyCurl/twt/simulate.py