Metadata-Version: 1.1
Name: twtPyCurl
Version: 1.1.1
Summary: A pycurl interface to Twitter’s rest and streaming API’s
Home-page: https://github.com/nickmilon/twtPyCurl
Author: @nickmilon
Author-email: nickmilon/gmail/com
License: GPL3
Download-URL: https://github.com/nickmilon/twtPyCurl/tarball/master
Keywords: Twitter,API,REST,STREAM,HTTP,python
Platform: UNKNOWN
Classifier: Development Status :: 4 - Beta
Classifier: Intended Audience :: Developers
Classifier: License :: OSI Approved :: Apache Software License
Classifier: Operating System :: MacOS :: MacOS X
Classifier: Operating System :: Microsoft :: Windows
Classifier: Operating System :: POSIX
Classifier: Programming Language :: Python :: 2.7
Classifier: Programming Language :: Python :: 3.4
Classifier: Topic :: Software Development :: Libraries
